imoji/__init__.py
imoji/entry.py
imoji/imoji.py
imoji-0.1.0.dist-info/METADATA
imoji-0.1.0.dist-info/WHEEL
imoji-0.1.0.dist-info/top_level.txt
imoji-0.1.0.dist-info/RECORD
