Metadata-Version: 2.1
Name: imoji
Version: 0.1.0
Summary: A emoji lib for image manipulation which works with pillow library.
Home-page: UNKNOWN
Author: Caio Madeira
License: MIT
Platform: UNKNOWN
Requires-Dist: pillow
